claritea.py
claritea-0.1.2.dist-info/METADATA
claritea-0.1.2.dist-info/WHEEL
claritea-0.1.2.dist-info/entry_points.txt
claritea-0.1.2.dist-info/top_level.txt
claritea-0.1.2.dist-info/RECORD
