Metadata-Version: 2.4
Name: claritea
Version: 0.1.2
Summary: Bundle source code into an LLM friendly format
Requires-Python: >=3.11
Requires-Dist: gitpython>=3.1.44
